customers_data/__init__.py
customers_data/__main__.py
customers_data/utils.py
customers_data_cupack-0.3.0.dist-info/METADATA
customers_data_cupack-0.3.0.dist-info/WHEEL
customers_data_cupack-0.3.0.dist-info/top_level.txt
customers_data_cupack-0.3.0.dist-info/RECORD
